.coveragerc
.gitignore
.travis.yml
COPYING
README.md
pylintrc
requirements.txt
setup.cfg
setup.py
test_requirements.txt
aloe_django/__init__.py
aloe_django/runner.py
aloe_django.egg-info/PKG-INFO
aloe_django.egg-info/SOURCES.txt
aloe_django.egg-info/dependency_links.txt
aloe_django.egg-info/requires.txt
aloe_django.egg-info/top_level.txt
aloe_django/management/__init__.py
aloe_django/management/commands/__init__.py
aloe_django/management/commands/harvest.py
aloe_django/steps/__init__.py
aloe_django/steps/mail.py
aloe_django/steps/models.py
docs/Makefile
docs/conf.py
docs/harvest.rst
docs/index.rst
docs/porting.rst
docs/steps.rst
docs/using.rst
tests/__init__.py
tests/util.py
tests/integration/__init__.py
tests/integration/test_harvest.py
tests/integration/test_mail_steps.py
tests/integration/test_model_steps.py
tests/integration/test_stock_app.py
tests/integration/django/alfaces/__init__.py
tests/integration/django/alfaces/manage.py
tests/integration/django/alfaces/settings.py
tests/integration/django/alfaces/urls.py
tests/integration/django/alfaces/donothing/__init__.py
tests/integration/django/alfaces/donothing/models.py
tests/integration/django/alfaces/donothing/tests.py
tests/integration/django/alfaces/donothing/views.py
tests/integration/django/alfaces/donothing/features/__init__.py
tests/integration/django/alfaces/donothing/features/dumb-page.feature
tests/integration/django/alfaces/donothing/features/simple_steps.py
tests/integration/django/alfaces/donothing/templates/index.html
tests/integration/django/alfaces/foobar/__init__.py
tests/integration/django/alfaces/foobar/models.py
tests/integration/django/alfaces/foobar/features/__init__.py
tests/integration/django/alfaces/foobar/features/foobar.feature
tests/integration/django/alfaces/foobar/features/foobar_steps.py
tests/integration/django/alfaces/foobar/features/deeper/deeper/leaf.feature
tests/integration/django/bamboo/__init__.py
tests/integration/django/bamboo/manage.py
tests/integration/django/bamboo/settings.py
tests/integration/django/bamboo/urls.py
tests/integration/django/bamboo/leaves/__init__.py
tests/integration/django/bamboo/leaves/features/__init__.py
