Metadata-Version: 1.1
Name: aloe-django
Version: 0.0.20
Summary: Package for testing Django applications with Aloe
Home-page: https://github.com/aloetesting/aloe_django
Author: Alexey Kotlyarov
Author-email: a@koterpillar.com
License: UNKNOWN
Platform: UNKNOWN
Classifier: License :: OSI Approved :: GNU General Public License v3 or later (GPLv3+)
Classifier: Programming Language :: Python
Classifier: Programming Language :: Python :: 2
Classifier: Programming Language :: Python :: 3
